Workbook

Sheet Capa
A1: SMARTINVEST BANK
A4: DOCUMENTAÇÃO PROFISSIONAL DO PROJETO
A6: Empresa | B6: SmartInvest Bank
A7: Ramo | B7: Tecnologia Financeira (fintech)
A8: Objetivo | B8: Plataforma digital para educação financeira e simulação de investimentos.
A9: Versão | B9: 1.0
A10: Data | B10: 28/09/2026
A13: Integrantes
A14: Nome | B14: RA | C14: Função
A15: Samuel Ferreira de Lima | B15: Não informado | C15: Tech Lead
A16: Eric da Silva Rodrigues | B16: Não informado | C16: Analista de Dados
A17: Lucas Rangel Lopes | B17: Não informado | C17: Gerente de Projetos
A18: Fernando de Morais Gomes | B18: Não informado | C18: Analista de Cibersegurança
A19: Lucas Thiago Magalhães Rocha | B19: Não informado | C19: Analista de Cibersegurança
A20: Julio Rocha Lipa | B20: Não informado | C20: Gerente de Projetos
A21: Matheus Saloio dos Santos Domingos Silveira | B21: Não informado | C21: Gerente de Projetos
A22: Pablo Faustino de Melo Silva | B22: Não informado | C22: Analista PO
A23: Gustavo Figueiredo Alexandre | B23: Não informado | C23: Analista de Dados
A24: Guilherme Augusto Schmidt Pereira | B24: Não informado | C24: Analista PO

Sheet 01_TAP
B1: TAP – TERMO DE ABERTURA DO PROJETO
B3: Nome do projeto | C3: SmartInvest Bank
B4: Patrocinador | C4: A definir pela instituição de ensino / grupo
B5: Gerente do projeto | C5: Samuel Ferreira de Lima
B6: Objetivo | C6: Desenvolver uma plataforma digital de educação financeira e simulação de investimentos, permitindo ao usuário administrar uma carteira virtual, realizar transações simuladas e receber recomendações conforme seu perfil de risco.
B7: Justificativa | C7: Facilitar a compreensão de investimentos e apoiar decisões financeiras por meio de um ambiente digital seguro, didático e orientado ao perfil do usuário.
B8: Escopo incluído | C8: Cadastro/login; perfil de investidor; carteira virtual; operações simuladas; recomendações por regras; dashboard; relatórios; conteúdos educacionais; administração; logs; testes e documentação.
B9: Fora do escopo | C9: Operações financeiras reais, custódia de recursos, execução de ordens reais, promessa de rentabilidade e aconselhamento financeiro individualizado.
B10: Premissas | C10: Dados de mercado podem ser simulados; equipe com disponibilidade acadêmica; requisitos serão validados pelos integrantes; solução será tratada como protótipo acadêmico.
B11: Restrições | C11: Prazo acadêmico; orçamento estimado; disponibilidade limitada da equipe; necessidade de ferramentas acessíveis.
B12: Riscos principais | C12: Mudança de requisitos; atraso de desenvolvimento; falhas de segurança; inconsistências em regras de recomendação; indisponibilidade de dados/serviços.
B13: Critérios de sucesso | C13: Entregas concluídas conforme EAP; requisitos críticos implementados; testes aprovados; documentação completa; apresentação realizada.
B14: Entregáveis | C14: TAP, EAP, Backlog, RACI, Gantt, Gestão de Custos, protótipo/solução, testes e documentação final.

Sheet 02_EAP
B1: EAP – ESTRUTURA ANALÍTICA DO PROJETO
B3: Código | C3: Pacote / Entrega | D3: Descrição
B4: 1 | C4: SmartInvest Bank – Projeto | D4: Projeto completo
B5: 1.1 | C5: Iniciação | D5: Formalização e definição inicial
B6: 1.1.1 | C6: Termo de Abertura do Projeto | D6: Documento de autorização do projeto
B7: 1.1.2 | C7: Identificação das partes interessadas | D7: Stakeholders e necessidades
B8: 1.2 | C8: Planejamento | D8: Planejamento do produto e do projeto
B9: 1.2.1 | C9: Levantamento de requisitos | D9: Requisitos funcionais e não funcionais
B10: 1.2.2 | C10: Backlog do produto | D10: Priorização das necessidades
B11: 1.2.3 | C11: Arquitetura da solução | D11: Definição da estrutura técnica
B12: 1.2.4 | C12: Plano de cronograma e custos | D12: Estimativas e linha de base
B13: 1.3 | C13: UX/UI e prototipação | D13: Experiência e interface
B14: 1.3.1 | C14: Fluxos de usuário | D14: Jornadas principais
... B31: 1.6.3 | C31: Apresentação e encerramento | D31: Entrega acadêmica e lições aprendidas

Sheet 03_Backlog
B1: BACKLOG DO PROJETO
B3: ID | C3: Necessidade / História | D3: Usuário | E3: Descrição | F3: Classificação | G3: Prioridade | H3: Critério de aceite
B4: 1 | C4: Cadastro e login seguro | D4: Usuário | E4: Permitir criação de conta e acesso autenticado à plataforma. | F4: Must Have | G4: Alta | H4: Funcionalidade disponível e validada em teste.
B5: 2 | C5: Perfil de investidor | D5: Usuário | E5: Identificar o perfil de risco por meio de questionário. | F5: Must Have | G5: Alta | H5: Funcionalidade disponível e validada em teste.
B6: 3 | C6: Carteira virtual | D6: Usuário | E6: Visualizar e administrar uma carteira de investimentos simulada. | F6: Must Have | G6: Alta | H6: Funcionalidade disponível e validada em teste.
B7: 4 | C7: Simulação de compra e venda | D7: Usuário | E7: Executar operações simuladas de compra e venda de ativos. | F7: Must Have | G7: Alta | H7: Funcionalidade disponível e validada em teste.
B8: 5 | C8: Recomendações por perfil | D8: Usuário | E8: Receber sugestões educacionais de investimentos compatíveis com o perfil. | F8: Must Have | G8: Alta | H8: Funcionalidade disponível e validada em teste.
B9: 6 | C9: Dashboard financeiro | D9: Usuário | E9: Visualizar saldo, patrimônio, rentabilidade e distribuição da carteira. | F9: Must Have | G9: Alta | H9: Funcionalidade disponível e validada em teste.
B10: 7 | C10: Histórico de transações | D10: Usuário | E10: Consultar operações e movimentações realizadas na simulação. | F10: Should Have | G10: Média | H10: Funcionalidade implementada e validada conforme requisito.
B11: 8 | C11: Relatórios de desempenho | D11: Usuário | E11: Gerar análises de rentabilidade e evolução da carteira. | F11: Should Have | G11: Média | H11: Funcionalidade implementada e validada conforme requisito.
B12: 9 | C12: Conteúdo de educação financeira | D12: Usuário | E12: Disponibilizar conteúdos para explicar conceitos financeiros e de investimentos. | F12: Should Have | G12: Média | H12: Funcionalidade implementada e validada conforme requisito.
B13: 10 | C13: Alertas e notificações | D13: Usuário | E13: Informar alterações relevantes na carteira e eventos da simulação. | F13: Could Have | G13: Baixa | H13: Funcionalidade implementada e validada conforme requisito.
B14: 11 | C14: Administração de usuários | D14: Administrador | E14: Gerenciar usuários, permissões e dados básicos da plataforma. | F14: Must Have | G14: Alta | H14: Funcionalidade disponível e validada em teste.
B15: 12 | C15: Auditoria e logs | D15: Administrador | E15: Registrar eventos relevantes para rastreabilidade e segurança. | F15: Must Have | G15: Alta | H15: Funcionalidade disponível e validada em teste.
... B17: 14 | C17: Teste de usabilidade | D17: Equipe | E17: Validar facilidade de uso com cenários de teste. | F17: Should Have | G17: Média | H17: Funcionalidade implementada e validada conforme requisito.

Sheet 04_RACI
A1: MATRIZ RACI
A3: Atividade | B3: Samuel Ferreira de Lima | C3: Eric da Silva Rodrigues | D3: Lucas Rangel Lopes | E3: Fernando de Morais Gomes | F3: Lucas Thiago Magalhães Rocha | G3: Julio Rocha Lipa | H3: Matheus Saloio dos Santos Domingos Silveira | I3: Pablo Faustino de Melo Silva | J3: Gustavo Figueiredo Alexandre | K3: Guilherme Augusto Schmidt Pereira
B4: =_xlfn.XLOOKUP(B3,Capa!$A$14:$A$24,Capa!$C$14:$C$24,"") -> Tech Lead | C4: =_xlfn.XLOOKUP(C3,Capa!$A$14:$A$24,Capa!$C$14:$C$24,"") -> Analista de Dados | D4: =_xlfn.XLOOKUP(D3,Capa!$A$14:$A$24,Capa!$C$14:$C$24,"") -> Gerente de Projetos | E4: =_xlfn.XLOOKUP(E3,Capa!$A$14:$A$24,Capa!$C$14:$C$24,"") -> Analista de Cibersegurança | F4: =_xlfn.XLOOKUP(F3,Capa!$A$14:$A$24,Capa!$C$14:$C$24,"") -> Analista de Cibersegurança | G4: =_xlfn.XLOOKUP(G3,Capa!$A$14:$A$24,Capa!$C$14:$C$24,"") -> Gerente de Projetos | H4: =_xlfn.XLOOKUP(H3,Capa!$A$14:$A$24,Capa!$C$14:$C$24,"") -> Gerente de Projetos | I4: =_xlfn.XLOOKUP(I3,Capa!$A$14:$A$24,Capa!$C$14:$C$24,"") -> Analista PO | ... K4: =_xlfn.XLOOKUP(K3,Capa!$A$14:$A$24,Capa!$C$14:$C$24,"") -> Analista PO
A5: TAP e planejamento do projeto | B5: A/R | C5: I | D5: R | E5: I | F5: I | G5: R | H5: R | I5: I | J5: I | K5: I
A6: Levantamento de requisitos | B6: A/C | C6: C | D6: C | E6: C | F6: C | G6: C | H6: C | I6: C | J6: C | K6: C
A7: Backlog e priorização | B7: A | C7: I | D7: R | E7: I | F7: I | G7: R | H7: R | I7: I | J7: I | K7: I
A8: Arquitetura da solução | B8: A/R | C8: I | D8: I | E8: I | F8: I | G8: I | H8: I | I8: I | J8: I | K8: I
A9: UX/UI e protótipos | B9: A/R | C9: R/C | D9: I | E9: C | F9: C | G9: I | H9: I | I9: C | J9: R/C | K9: C
A10: Autenticação e usuários | B10: A/R | C10: C | D10: I | E10: C | F10: C | G10: I | H10: I | I10: I | J10: C | K10: I
A11: Carteira e simulação | B11: A/R | C11: C | D11: I | E11: I | F11: I | G11: I | H11: I | I11: I | J11: C | K11: I
A12: Recomendações de investimentos | B12: A/R | C12: C | D12: I | E12: I | F12: I | G12: I | H12: I | I12: I | J12: C | K12: I
A13: Dashboard e relatórios | B13: A | C13: R | D13: I | E13: I | F13: I | G13: I | H13: I | I13: I | J13: R | K13: I
A14: Segurança e auditoria | B14: A | C14: I | D14: I | E14: R | F14: R | G14: I | H14: I | I14: I | J14: I | K14: I
A15: Testes funcionais | B15: A/R | C15: R | D15: I | E15: R | F15: R | G15: I | H15: I | I15: R | J15: R | K15: R
A16: Testes de segurança | B16: A | C16: I | D16: I | E16: R | F16: R | G16: I | H16: I | I16: I | J16: I | K16: I
... A19: Apresentação e encerramento | B19: A/R | C19: R | D19: R | E19: R | F19: R | G19: R | H19: R | I19: R | J19: R | K19: R
A22: Legenda
A23: R = Responsible (Executa) | A = Accountable (Responsável final) | C = Consulted (Consultado) | I = Informed (Informado)

Sheet 05_Gantt
A1: GESTÃO DO CRONOGRAMA – GANTT
A3: Atividade | B3: Início | C3: Fim | D3: Duração (dias) | E3: 46300 | F3: 46301 | G3: 46302 | H3: 46303 | I3: 46304 | J3: 46305 | K3: 46306 | L3: 46307 | M3: 46308 | N3: 46309 | O3: 46310 | P3: 46311 | Q3: 46312 | R3: 46313 | S3: 46314 | T3: 46315 | U3: 46316 | V3: 46317 | W3: 46318 | X3: 46319 | Y3: 46320 | Z3: 46321 | AA3: 46322 | AB3: 46323 | AC3: 46324 | AD3: 46325 | AE3: 46326 | AF3: 46327 | AG3: 46328 | AH3: 46329 | AI3: 46330 | AJ3: 46331 | AK3: 46332 | AL3: 46333 | AM3: 46334 | AN3: 46335 | AO3: 46336 | AP3: 46337 | AQ3: 46338 | AR3: 46339 | AS3: 46340 | AT3: 46341 | AU3: 46342 | AV3: 46343 | AW3: 46344 | AX3: 46345 | AY3: 46346 | AZ3: 46347 | BA3: 46348 | BB3: 46349 | BC3: 46350 | BD3: 46351 | BE3: 46352 | BF3: 46353 | BG3: 46354 | BH3: 46355 | BI3: 46356 | BJ3: 46357 | BK3: 46358 | BL3: 46359 | BM3: 46360 | BN3: 46361 | BO3: 46362 | BP3: 46363 | BQ3: 46364 | BR3: 46365 | BS3: 46366 | BT3: 46367 | BU3: 46368 | BV3: 46369 | BW3: 46370 | BX3: 46371 | BY3: 46372 | BZ3: 46373 | CA3: 46374 | CB3: 46375 | CC3: 46376 | CD3: 46377 | CE3: 46378 | CF3: 46379 | CG3: 46380 | CH3: 46381 | CI3: 46382 | CJ3: 46383 | CK3: 46384 | CL3: 46385 | CM3: 46386 | CN3: 46387 | CO3: 46388 | CP3: 46389 | CQ3: 46390 | CR3: 46391 | CS3: 46392 | CT3: 46393 | CU3: 46394 | CV3: 46395 | CW3: 46396 | CX3: 46397
A4: Iniciação e TAP | B4: 46239 | C4: =B4+3 -> 46242 | D4: 3
A5: Levantamento de requisitos | B5: =B4+5 -> 46244 | C5: =B5+3 -> 46247 | D5: 3
A6: Backlog e priorização | B6: =B5+5 -> 46249 | C6: =B6+3 -> 46252 | D6: 3
A7: Arquitetura da solução | B7: =B6+5 -> 46254 | C7: =B7+3 -> 46257 | D7: 3
A8: UX/UI e protótipos | B8: =B7+5 -> 46259 | C8: =B8+3 -> 46262 | D8: 3
A9: Autenticação e usuários | B9: =B8+5 -> 46264 | C9: =B9+3 -> 46267 | D9: 3
A10: Perfil de investidor | B10: =B9+5 -> 46269 | C10: =B10+3 -> 46272 | D10: 3
A11: Carteira virtual | B11: =B10+5 -> 46274 | C11: =B11+3 -> 46277 | D11: 3
A12: Simulação de operações | B12: =B11+5 -> 46279 | C12: =B12+3 -> 46282 | D12: 3
A13: Recomendações por perfil | B13: =B12+5 -> 46284 | C13: =B13+3 -> 46287 | D13: 3
A14: Dashboard e relatórios | B14: =B13+5 -> 46289 | C14: =B14+3 -> 46292 | D14: 3
A15: Educação financeira | B15: =B14+5 -> 46294 | C15: =B15+3 -> 46297 | D15: 3
A16: Segurança, logs e auditoria | B16: =B15+5 -> 46299 | C16: =B16+3 -> 46302 | D16: 3
... A22: Apresentação e encerramento | B22: =B21+5 -> 46329 | C22: =B22+3 -> 46332 | D22: 3

Sheet 06_Custos
A1: GESTÃO DE CUSTOS
A3: Item | B3: Valor/hora (R$) | C3: Horas / Quantidade | D3: Custo total (R$) | E3: Observação
A4: Gerenciamento do projeto | B4: 60 | C4: 50 | D4: =B4*C4 -> 3000
A5: Análise de requisitos | B5: 50 | C5: 24 | D5: =B5*C5 -> 1200
A6: Arquitetura e desenvolvimento | B6: 80 | C6: 120 | D6: =B6*C6 -> 9600
A7: UX/UI e prototipação | B7: 55 | C7: 35 | D7: =B7*C7 -> 1925
A8: Testes e qualidade | B8: 55 | C8: 50 | D8: =B8*C8 -> 2750
A9: Segurança e auditoria | B9: 75 | C9: 30 | D9: =B9*C9 -> 2250
A10: Documentação e apresentação | B10: 45 | C10: 25 | D10: =B10*C10 -> 1125
A11: Infraestrutura/serviços de desenvolvimento | B11: 40 | C11: 20 | D11: =B11*C11 -> 800
A12: TOTAL ESTIMADO | D12: =SUM(D4:D11) -> 22650 | E12: > valores podem variar

Sheet 07_Dashboard
A1: PAINEL EXECUTIVO
A3: Projeto | B3: SmartInvest Bank | F3: Distribuição do Backlog por prioridade
A4: Total de backlog items | B4: 14 | F4: Prioridade | G4: Quantidade
A5: Itens prioridade alta | B5: 9 | F5: Alta | G5: 9
A6: Pacotes EAP | B6: 29 | F6: Média | G6: 4
A7: Atividades no Gantt | B7: 19 | F7: Baixa | G7: 1
A8: Custo estimado | B8: R$ 23.700,00
A9: Duração planejada | B9: 98 dias
